upsert_slr/__init__.py
upsert_slr/py.typed
upsert_slr/_jsii/__init__.py
upsert_slr/_jsii/upsert-slr@1.0.7.jsii.tgz
upsert_slr-1.0.7.dist-info/LICENSE
upsert_slr-1.0.7.dist-info/METADATA
upsert_slr-1.0.7.dist-info/WHEEL
upsert_slr-1.0.7.dist-info/top_level.txt
upsert_slr-1.0.7.dist-info/RECORD
